[
    {
        "client_msg_id": "c42512bf-f32b-4147-8ccd-9951a50d25c1",
        "type": "message",
        "text": "<@U03Q17LBJP3> ９４泉や本人より修正依頼きました\n台本の上の方にメモってありますー",
        "user": "U03CXUXB5PF",
        "ts": "1683631433.597659",
        "blocks": [
            {
                "type": "rich_text",
                "block_id": "WsaAB",
                "elements": [
                    {
                        "type": "rich_text_section",
                        "elements": [
                            {
                                "type": "user",
                                "user_id": "U03Q17LBJP3"
                            },
                            {
                                "type": "text",
                                "text": " ９４泉や本人より修正依頼きました\n台本の上の方にメモってありますー"
                            }
                        ]
                    }
                ]
            }
        ],
        "team": "T03CU6RQ154",
        "user_team": "T03CU6RQ154",
        "source_team": "T03CU6RQ154",
        "user_profile": {
            "avatar_hash": "27fb9284d11c",
            "image_72": "https:\/\/avatars.slack-edge.com\/2022-04-26\/3440019395589_27fb9284d11c008928ea_72.png",
            "first_name": "h.kodera",
            "real_name": "h.kodera",
            "display_name": "dela",
            "team": "T03CU6RQ154",
            "name": "h.kodera",
            "is_restricted": false,
            "is_ultra_restricted": false
        },
        "reactions": [
            {
                "name": "apple",
                "users": [
                    "U03Q17LBJP3"
                ],
                "count": 1
            }
        ]
    },
    {
        "type": "message",
        "text": "<@U03V84JSHNK>\n94泉谷 本人修正よりCGの直しをお願いしたいです。",
        "files": [
            {
                "id": "F056W2KSQSX",
                "created": 1683633736,
                "timestamp": 1683633736,
                "name": "image.png",
                "title": "image.png",
                "mimetype": "image\/png",
                "filetype": "png",
                "pretty_type": "PNG",
                "user": "U03Q17LBJP3",
                "user_team": "T03CU6RQ154",
                "editable": false,
                "size": 8881,
                "mode": "hosted",
                "is_external": false,
                "external_type": "",
                "is_public": true,
                "public_url_shared": false,
                "display_as_bot": false,
                "username": "",
                "url_private": "https:\/\/files.slack.com\/files-pri\/T03CU6RQ154-F056W2KSQSX\/image.png?t=xoxe-3436229817174-5500262048449-5500262224001-b121e2a5a84594a3b8db7542afc8fcc6",
                "url_private_download": "https:\/\/files.slack.com\/files-pri\/T03CU6RQ154-F056W2KSQSX\/download\/image.png?t=xoxe-3436229817174-5500262048449-5500262224001-b121e2a5a84594a3b8db7542afc8fcc6",
                "media_display_type": "unknown",
                "thumb_64": "https:\/\/files.slack.com\/files-tmb\/T03CU6RQ154-F056W2KSQSX-fdf4f1701b\/image_64.png?t=xoxe-3436229817174-5500262048449-5500262224001-b121e2a5a84594a3b8db7542afc8fcc6",
                "thumb_80": "https:\/\/files.slack.com\/files-tmb\/T03CU6RQ154-F056W2KSQSX-fdf4f1701b\/image_80.png?t=xoxe-3436229817174-5500262048449-5500262224001-b121e2a5a84594a3b8db7542afc8fcc6",
                "thumb_360": "https:\/\/files.slack.com\/files-tmb\/T03CU6RQ154-F056W2KSQSX-fdf4f1701b\/image_360.png?t=xoxe-3436229817174-5500262048449-5500262224001-b121e2a5a84594a3b8db7542afc8fcc6",
                "thumb_360_w": 360,
                "thumb_360_h": 23,
                "thumb_480": "https:\/\/files.slack.com\/files-tmb\/T03CU6RQ154-F056W2KSQSX-fdf4f1701b\/image_480.png?t=xoxe-3436229817174-5500262048449-5500262224001-b121e2a5a84594a3b8db7542afc8fcc6",
                "thumb_480_w": 480,
                "thumb_480_h": 31,
                "thumb_160": "https:\/\/files.slack.com\/files-tmb\/T03CU6RQ154-F056W2KSQSX-fdf4f1701b\/image_160.png?t=xoxe-3436229817174-5500262048449-5500262224001-b121e2a5a84594a3b8db7542afc8fcc6",
                "original_w": 659,
                "original_h": 43,
                "thumb_tiny": "AwADADDQP38U1unU04\/6ymt900AA5Jz6U48D8KavU\/SnHp+FAAaVKQ0qUAf\/2Q==",
                "permalink": "https:\/\/kdddipresidentnep2022.slack.com\/files\/U03Q17LBJP3\/F056W2KSQSX\/image.png",
                "permalink_public": "https:\/\/slack-files.com\/T03CU6RQ154-F056W2KSQSX-77ceb59099",
                "is_starred": false,
                "has_rich_preview": false,
                "file_access": "visible"
            }
        ],
        "upload": false,
        "user": "U03Q17LBJP3",
        "display_as_bot": false,
        "ts": "1683633880.069949",
        "blocks": [
            {
                "type": "rich_text",
                "block_id": "1\/8H",
                "elements": [
                    {
                        "type": "rich_text_section",
                        "elements": [
                            {
                                "type": "user",
                                "user_id": "U03V84JSHNK"
                            },
                            {
                                "type": "text",
                                "text": "\n94泉谷 本人修正よりCGの直しをお願いしたいです。"
                            }
                        ]
                    }
                ]
            }
        ],
        "client_msg_id": "c3d3aec8-9035-4fd7-974e-3a674ef8d160",
        "thread_ts": "1683633880.069949",
        "reply_count": 2,
        "reply_users_count": 1,
        "latest_reply": "1683700884.745889",
        "reply_users": [
            "U03V84JSHNK"
        ],
        "replies": [
            {
                "user": "U03V84JSHNK",
                "ts": "1683633961.046869"
            },
            {
                "user": "U03V84JSHNK",
                "ts": "1683700884.745889"
            }
        ],
        "is_locked": false,
        "subscribed": false
    },
    {
        "client_msg_id": "6d10d6e4-d7d0-4149-bc59-e9fbfd7a735a",
        "type": "message",
        "text": "<@U03Q17LBJP3> 了解しました。発注します。",
        "user": "U03V84JSHNK",
        "ts": "1683633961.046869",
        "blocks": [
            {
                "type": "rich_text",
                "block_id": "osUI",
                "elements": [
                    {
                        "type": "rich_text_section",
                        "elements": [
                            {
                                "type": "user",
                                "user_id": "U03Q17LBJP3"
                            },
                            {
                                "type": "text",
                                "text": " 了解しました。発注します。"
                            }
                        ]
                    }
                ]
            }
        ],
        "team": "T03CU6RQ154",
        "user_team": "T03CU6RQ154",
        "source_team": "T03CU6RQ154",
        "user_profile": {
            "avatar_hash": "df79dee44905",
            "image_72": "https:\/\/avatars.slack-edge.com\/2022-08-31\/4004709043478_df79dee449054ec9db85_72.png",
            "first_name": "Ryousuke",
            "real_name": "Ryousuke Yasunaga",
            "display_name": "Ryousuke Yasunaga",
            "team": "T03CU6RQ154",
            "name": "ya63su",
            "is_restricted": false,
            "is_ultra_restricted": false
        },
        "thread_ts": "1683633880.069949",
        "parent_user_id": "U03Q17LBJP3",
        "reactions": [
            {
                "name": "apple",
                "users": [
                    "U03Q17LBJP3"
                ],
                "count": 1
            }
        ]
    },
    {
        "client_msg_id": "a0f655f8-47dd-4420-afdf-5b21e7a9106a",
        "type": "message",
        "text": "<@U03Q17LBJP3> <https:\/\/www.dropbox.com\/s\/00xqkv906e8nzak\/CG_94izumiya_%E4%BF%AE%E6%AD%A3_20230510_motomiya%20%E6%9C%AC%E5%AE%AE%E4%B8%80%E6%85%B6.zip?dl=0>\nCG修正入りました。よろしくお願いいたします。",
        "user": "U03V84JSHNK",
        "ts": "1683700884.745889",
        "blocks": [
            {
                "type": "rich_text",
                "block_id": "x+oXT",
                "elements": [
                    {
                        "type": "rich_text_section",
                        "elements": [
                            {
                                "type": "user",
                                "user_id": "U03Q17LBJP3"
                            },
                            {
                                "type": "text",
                                "text": " "
                            },
                            {
                                "type": "link",
                                "url": "https:\/\/www.dropbox.com\/s\/00xqkv906e8nzak\/CG_94izumiya_%E4%BF%AE%E6%AD%A3_20230510_motomiya%20%E6%9C%AC%E5%AE%AE%E4%B8%80%E6%85%B6.zip?dl=0"
                            },
                            {
                                "type": "text",
                                "text": "\nCG修正入りました。よろしくお願いいたします。"
                            }
                        ]
                    }
                ]
            }
        ],
        "team": "T03CU6RQ154",
        "user_team": "T03CU6RQ154",
        "source_team": "T03CU6RQ154",
        "user_profile": {
            "avatar_hash": "df79dee44905",
            "image_72": "https:\/\/avatars.slack-edge.com\/2022-08-31\/4004709043478_df79dee449054ec9db85_72.png",
            "first_name": "Ryousuke",
            "real_name": "Ryousuke Yasunaga",
            "display_name": "Ryousuke Yasunaga",
            "team": "T03CU6RQ154",
            "name": "ya63su",
            "is_restricted": false,
            "is_ultra_restricted": false
        },
        "thread_ts": "1683633880.069949",
        "parent_user_id": "U03Q17LBJP3",
        "reactions": [
            {
                "name": "apple",
                "users": [
                    "U03Q17LBJP3"
                ],
                "count": 1
            }
        ]
    }
]